.travis.yml
CHANGES.rst
LICENSE.txt
README.rst
pytest.ini
setup.py
tox.ini
src/subprocess_middleware/__init__.py
src/subprocess_middleware/response.py
src/subprocess_middleware/tween.py
src/subprocess_middleware/worker.py
src/subprocess_middleware/wsgi.py
src/subprocess_middleware.egg-info/PKG-INFO
src/subprocess_middleware.egg-info/SOURCES.txt
src/subprocess_middleware.egg-info/dependency_links.txt
src/subprocess_middleware.egg-info/requires.txt
src/subprocess_middleware.egg-info/top_level.txt
src/subprocess_middleware.egg-info/zip-safe
src/subprocess_middleware/tests/__init__.py
src/subprocess_middleware/tests/conftest.py
src/subprocess_middleware/tests/test_subprocess_middleware.py
src/subprocess_middleware/tests/testing.py
src/subprocess_middleware/tests/testing_transform.py