Metadata-Version: 1.0
Name: subprocess-middleware
Version: 0.3
Summary: Subprocess WSGI middleware and Pyramid tween.
Home-page: http://github.com/lrowe/subprocess_middleware
Author: Laurence Rowe
Author-email: laurence@lrowe.co.uk
License: MIT
Platform: UNKNOWN
